minion_works-0.0.1.dist-info/licenses/LICENSE
src/__init__.py
src/config/__init__.py
src/config/settings.py
tests/__init__.py
tests/test_content_extraction.py
tests/test_google_search.py
tests/test_navigation.py
tests/test_orchestrator.py
minion_works-0.0.1.dist-info/METADATA
minion_works-0.0.1.dist-info/WHEEL
minion_works-0.0.1.dist-info/top_level.txt
minion_works-0.0.1.dist-info/RECORD
