Metadata-Version: 2.4
Name: minion-works
Version: 0.0.1
Summary: Agents for menial tasks
Home-page: https://github.com/minionworks/minions
Author: Aman, Cheena, Sai
Author-email: sai@cobuild.tech
License: MIT
Classifier: Programming Language :: Python :: 3
Classifier: License :: OSI Approved :: MIT License
Classifier: Operating System :: OS Independent
Requires-Python: >=3.7
License-File: LICENSE
Requires-Dist: asyncio
Requires-Dist: playwright
Requires-Dist: openai
Requires-Dist: markdownify
Requires-Dist: python-dotenv
Requires-Dist: langchain-core
Dynamic: author
Dynamic: author-email
Dynamic: classifier
Dynamic: description
Dynamic: description-content-type
Dynamic: home-page
Dynamic: license
Dynamic: license-file
Dynamic: requires-dist
Dynamic: requires-python
Dynamic: summary
